dbpystream/__init__.py
dbpystream/method.py
test/__init__.py
test/test.py
zqyTestFunction-1.0.0.dist-info/LICENSE
zqyTestFunction-1.0.0.dist-info/METADATA
zqyTestFunction-1.0.0.dist-info/WHEEL
zqyTestFunction-1.0.0.dist-info/top_level.txt
zqyTestFunction-1.0.0.dist-info/RECORD
